mathmini/__init__.py
mathmini/__main__.py
mathmini/add.py
mathmini/mathmini.py
mathmini/sub.py
mathmini-1.0.3.dist-info/LICENSE
mathmini-1.0.3.dist-info/METADATA
mathmini-1.0.3.dist-info/WHEEL
mathmini-1.0.3.dist-info/top_level.txt
mathmini-1.0.3.dist-info/RECORD
